<bpy>
  <Theme>
    <view_3d>
      <ThemeView3D object_active="#ffffff"
                   editmesh_active="#ffffff00"
                   act_spline="#c36c8c"
                   handle_align="#e277b1"
                   handle_sel_align="#ffffff"
                   handle_auto="#30b6e5"
                   handle_sel_auto="#ffffff"
                   bone_pose="#50c8ff"
                   bone_pose_active="#8cffff"
                   bone_solid="#c8c8c8"
                   bundle_solid="#c8c8c8"
                   camera="#000000"
                   camera_path="#000000"
                   frame_current="#53c03b"
                   edge_crease="#eb3bdd"
                   extra_edge_len="#200000"
                   edge_seam="#f0703b"
                   edge_select="#f3f3f3"
                   edge_sharp="#49a1ec"
                   edge_facesel="#272727"
                   empty="#000000"
                   face="#838383ff"
                   extra_face_angle="#cccccc"
                   extra_face_area="#cccccc"
                   face_dot="#52f27e"
                   facedot_size="3"
                   normal="#9cfcc8"
                   face_select="#949494ff"
                   handle_free="#cccccc"
                   handle_sel_free="#ffffff"
                   grid="#6e6e6e"
                   lamp="#ffe56666"
                   lastsel_point="#ffffff"
                   nurb_uline="#a3a3a3"
                   nurb_vline="#803060"
                   nurb_sel_uline="#ffffff"
                   nurb_sel_vline="#f090a0"
                   object_grouped="#63bd87"
                   object_grouped_active="#ffffff"
                   object_selected="#88fca7"
                   outline_width="1"
                   panel="#aaa8a6ff"
                   skin_root="#000000"
                   speaker="#000000"
                   transform="#ffffff"
                   handle_vect="#afafaf"
                   handle_sel_vect="#ffffff"
                   vertex="#343434"
                   vertex_normal="#68a1db"
                   vertex_select="#ff2f7a"
                   vertex_size="4"
                   wire="#242424">
        <space>
          <ThemeSpaceGeneric header="#aaa8a6"
                             header_text="#000000"
                             header_text_hi="#ffffff"
                             button="#aaa8a6"
                             button_text="#222222"
                             button_text_hi="#ffffff"
                             button_title="#313131"
                             text="#ffffff"
                             text_hi="#ffffff"
                             title="#ffffff"
                             back="#918f8d">
          </ThemeSpaceGeneric>
        </space>
      </ThemeView3D>
    </view_3d>
    <clip_editor>
      <ThemeClipEditor active_marker="#ffffff"
                       frame_current="#a3ff96"
                       disabled_marker="#b54636"
                       grid="#5e5e5e"
                       handle_vertex="#000000"
                       handle_vertex_select="#ff2f7a"
                       handle_vertex_size="4"
                       locked_marker="#7f7f7f"
                       marker="#71cd7f"
                       marker_outline="#000000"
                       path_after="#5a7575"
                       path_before="#22d8d1"
                       selected_marker="#ff2f7a"
                       strips="#0c0a0a"
                       strips_selected="#ff8c00">
        <space>
          <ThemeSpaceGeneric header="#aaa8a6"
                             header_text="#000000"
                             header_text_hi="#ffffff"
                             button="#aaa8a6"
                             button_text="#222222"
                             button_text_hi="#ffffff"
                             button_title="#222222"
                             text="#1a1a1a"
                             text_hi="#ffffff"
                             title="#1a1a1a"
                             back="#aaa8a6">
          </ThemeSpaceGeneric>
        </space>
        <space_list>
          <ThemeSpaceListGeneric list="#666666"
                                 list_text="#000000"
                                 list_text_hi="#ffffff"
                                 list_title="#000000">
          </ThemeSpaceListGeneric>
        </space_list>
      </ThemeClipEditor>
    </clip_editor>
    <console>
      <ThemeConsole cursor="#9cfcc8"
                    line_error="#dc3a77"
                    line_info="#00aa00"
                    line_input="#ffffff"
                    line_output="#6080ff">
        <space>
          <ThemeSpaceGeneric header="#aaa8a6"
                             header_text="#000000"
                             header_text_hi="#ffffff"
                             button="#4d4d4d"
                             button_text="#131313"
                             button_text_hi="#ffffff"
                             button_title="#131313"
                             text="#000000"
                             text_hi="#ffffff"
                             title="#000000"
                             back="#0c0c0c">
          </ThemeSpaceGeneric>
        </space>
      </ThemeConsole>
    </console>
    <dopesheet_editor>
      <ThemeDopeSheet active_channels_group="#95adc1"
                      channel_group="#8a9dac"
                      channels="#9baeb9"
                      channels_selected="#91ccb3"
                      frame_current="#a3ff96"
                      dopesheet_channel="#9baeb9"
                      dopesheet_subchannel="#aaa8a6"
                      grid="#7f7f7f"
                      long_key="#0c0a0a"
                      long_key_selected="#ecfc37"
                      summary="#00000000"
                      value_sliders="#000000"
                      view_sliders="#333333">
        <space>
          <ThemeSpaceGeneric header="#aaa8a6"
                             header_text="#000000"
                             header_text_hi="#ffffff"
                             button="#aaa8a6"
                             button_text="#111111"
                             button_text_hi="#a3a3a3"
                             button_title="#111111"
                             text="#222222"
                             text_hi="#ffffff"
                             title="#ffffff"
                             back="#aaa8a6">
          </ThemeSpaceGeneric>
        </space>
        <space_list>
          <ThemeSpaceListGeneric list="#aaa8a6"
                                 list_text="#222222"
                                 list_text_hi="#ffffff"
                                 list_title="#cccccc">
          </ThemeSpaceListGeneric>
        </space_list>
      </ThemeDopeSheet>
    </dopesheet_editor>
    <file_browser>
      <ThemeFileBrowser active_file="#f1e593"
                        active_file_text="#ffffff"
                        scroll_handle="#8c8a88"
                        scrollbar="#4d4b4d"
                        selected_file="#f1e593"
                        tiles="#aaa8a6">
        <space>
          <ThemeSpaceGeneric header="#aaa8a6"
                             header_text="#afafaf"
                             header_text_hi="#ffffff"
                             button="#aaa8a6"
                             button_text="#cccccc"
                             button_text_hi="#ffffff"
                             button_title="#222222"
                             text="#222222"
                             text_hi="#ffffff"
                             title="#ffffff"
                             back="#aaa8a6">
          </ThemeSpaceGeneric>
        </space>
        <space_list>
          <ThemeSpaceListGeneric list="#aaa8a6"
                                 list_text="#7f7f7f"
                                 list_text_hi="#ffffff"
                                 list_title="#3a3a3a">
          </ThemeSpaceListGeneric>
        </space_list>
      </ThemeFileBrowser>
    </file_browser>
    <graph_editor>
      <ThemeGraphEditor active_channels_group="#95adc1"
                        handle_align="#1d1d1d"
                        handle_sel_align="#f3f3f3"
                        handle_auto="#696969"
                        handle_sel_auto="#d4d4d4"
                        handle_auto_clamped="#000000"
                        handle_sel_auto_clamped="#000000"
                        channel_group="#8a9dac"
                        channels_region="#4d4d4d"
                        frame_current="#a1ff8c"
                        dopesheet_channel="#aaa8a6"
                        dopesheet_subchannel="#aaa8a6"
                        handle_free="#252525"
                        handle_sel_free="#ececec"
                        grid="#8f8f8f"
                        handle_vertex="#525252"
                        handle_vertex_select="#f1f1f1"
                        handle_vertex_size="6"
                        lastsel_point="#000000"
                        panel="#989898"
                        handle_vect="#191919"
                        handle_sel_vect="#ffffff"
                        vertex="#575757"
                        vertex_select="#ffffff"
                        vertex_size="3"
                        window_sliders="#4d4d4d">
        <space>
          <ThemeSpaceGeneric header="#aaa8a6"
                             header_text="#000000"
                             header_text_hi="#ffffff"
                             button="#aaa8a6"
                             button_text="#222222"
                             button_text_hi="#ffffff"
                             button_title="#333333"
                             text="#222222"
                             text_hi="#ffffff"
                             title="#000000"
                             back="#aaa8a6">
          </ThemeSpaceGeneric>
        </space>
        <space_list>
          <ThemeSpaceListGeneric list="#aaa8a6"
                                 list_text="#222222"
                                 list_text_hi="#ffffff"
                                 list_title="#676767">
          </ThemeSpaceListGeneric>
        </space_list>
      </ThemeGraphEditor>
    </graph_editor>
    <image_editor>
      <ThemeImageEditor editmesh_active="#ffffff80"
                        face="#00000032"
                        face_dot="#ffffff"
                        facedot_size="2"
                        face_select="#ffffff3c"
                        scope_back="#aaa8a6ff"
                        preview_stitch_active="#e1d2c323"
                        preview_stitch_edge="#ff8500b2"
                        preview_stitch_face="#1242b026"
                        preview_stitch_stitchable="#00ff00ff"
                        preview_stitch_unstitchable="#ff0000ff"
                        preview_stitch_vert="#ff85007f"
                        vertex="#000000"
                        vertex_select="#ffffff"
                        vertex_size="3">
        <space>
          <ThemeSpaceGeneric header="#aaa8a6"
                             header_text="#000000"
                             header_text_hi="#ffffff"
                             button="#aaa8a6"
                             button_text="#222222"
                             button_text_hi="#ffffff"
                             button_title="#383838"
                             text="#ffffff"
                             text_hi="#ffffff"
                             title="#000000"
                             back="#2d2d2d">
          </ThemeSpaceGeneric>
        </space>
      </ThemeImageEditor>
    </image_editor>
    <info>
      <ThemeInfo>
        <space>
          <ThemeSpaceGeneric header="#aaa8a6"
                             header_text="#000000"
                             header_text_hi="#ffffff"
                             button="#aaa8a6"
                             button_text="#000000"
                             button_text_hi="#ffffff"
                             button_title="#000000"
                             text="#000000"
                             text_hi="#ffffff"
                             title="#000000"
                             back="#aaa8a6">
          </ThemeSpaceGeneric>
        </space>
      </ThemeInfo>
    </info>
    <logic_editor>
      <ThemeLogicEditor panel="#aaa8a6">
        <space>
          <ThemeSpaceGeneric header="#aaa8a6"
                             header_text="#000000"
                             header_text_hi="#ffffff"
                             button="#aaa8a6"
                             button_text="#222222"
                             button_text_hi="#ffffff"
                             button_title="#111111"
                             text="#222222"
                             text_hi="#ffffff"
                             title="#202020"
                             back="#aaa8a6">
          </ThemeSpaceGeneric>
        </space>
      </ThemeLogicEditor>
    </logic_editor>
    <nla_editor>
      <ThemeNLAEditor active_action="#00000000"
                      frame_current="#a3ff96"
                      grid="#a39f9c"
                      meta_strips="#000000"
                      meta_strips_selected="#000000"
                      active_action_unset="#00000000"
                      sound_strips="#000000"
                      sound_strips_selected="#000000"
                      strips="#000000"
                      strips_selected="#60c040"
                      transition_strips="#000000"
                      transition_strips_selected="#000000"
                      tweak="#000000"
                      tweak_duplicate="#000000"
                      view_sliders="#4d4d4d">
        <space>
          <ThemeSpaceGeneric header="#aaa8a6"
                             header_text="#a3a3a3"
                             header_text_hi="#cccccc"
                             button="#aaa8a6"
                             button_text="#000000"
                             button_text_hi="#ffffff"
                             button_title="#000000"
                             text="#333333"
                             text_hi="#ffffff"
                             title="#000000"
                             back="#aaa8a6">
          </ThemeSpaceGeneric>
        </space>
        <space_list>
          <ThemeSpaceListGeneric list="#aaa8a6"
                                 list_text="#000000"
                                 list_text_hi="#ffffff"
                                 list_title="#000000">
          </ThemeSpaceListGeneric>
        </space_list>
      </ThemeNLAEditor>
    </nla_editor>
    <node_editor>
      <ThemeNodeEditor node_active="#ffffff"
                       converter_node="#fffa90"
                       frame_node="#9a9b9ba0"
                       group_node="#ffc173"
                       in_out_node="#b1d9ff"
                       node_backdrop="#d4d4d4ff"
                       node_selected="#ffffff"
                       noodle_curving="5"
                       operator_node="#beffcb"
                       selected_text="#ffffff"
                       wire_select="#ffffff"
                       wire="#222222">
        <space>
          <ThemeSpaceGeneric header="#aaa8a6"
                             header_text="#333333"
                             header_text_hi="#ffffff"
                             button="#aaa8a6"
                             button_text="#222222"
                             button_text_hi="#c5c5c5"
                             button_title="#222222"
                             text="#222222"
                             text_hi="#ffffff"
                             title="#a3a3a3"
                             back="#aaa8a6">
          </ThemeSpaceGeneric>
        </space>
        <space_list>
          <ThemeSpaceListGeneric list="#4d4d4d"
                                 list_text="#676767"
                                 list_text_hi="#ffffff"
                                 list_title="#383838">
          </ThemeSpaceListGeneric>
        </space_list>
      </ThemeNodeEditor>
    </node_editor>
    <outliner>
      <ThemeOutliner match="#337f33"
                     selected_highlight="#870027">
        <space>
          <ThemeSpaceGeneric header="#aaa8a6"
                             header_text="#000000"
                             header_text_hi="#ffffff"
                             button="#aaa8a6"
                             button_text="#000000"
                             button_text_hi="#ffffff"
                             button_title="#0f0f0f"
                             text="#000000"
                             text_hi="#ffffff"
                             title="#ffffff"
                             back="#aaa8a6">
          </ThemeSpaceGeneric>
        </space>
      </ThemeOutliner>
    </outliner>
    <properties>
      <ThemeProperties panel="#aaa8a6">
        <space>
          <ThemeSpaceGeneric header="#aaa8a6"
                             header_text="#222222"
                             header_text_hi="#000000"
                             button="#aaa8a6"
                             button_text="#222222"
                             button_text_hi="#ffffff"
                             button_title="#222222"
                             text="#222222"
                             text_hi="#ffffff"
                             title="#222222"
                             back="#aaa8a6">
          </ThemeSpaceGeneric>
        </space>
      </ThemeProperties>
    </properties>
    <sequence_editor>
      <ThemeSequenceEditor audio_strip="#e0d2a0"
                           movieclip_strip="#20208f"
                           frame_current="#a3ff96"
                           draw_action="#50c8ff"
                           effect_strip="#be8c76"
                           grid="#afafaf"
                           image_strip="#c99ac0"
                           keyframe="#ffeb89"
                           meta_strip="#91918d"
                           movie_strip="#87a4c3"
                           preview_back="#000000"
                           scene_strip="#91b1a0"
                           transition_strip="#d9777a"
                           window_sliders="#777777">
        <space>
          <ThemeSpaceGeneric header="#aaa8a6"
                             header_text="#a3a3a3"
                             header_text_hi="#ffffff"
                             button="#aaa8a6"
                             button_text="#111111"
                             button_text_hi="#ffffff"
                             button_title="#111111"
                             text="#333333"
                             text_hi="#ffffff"
                             title="#000000"
                             back="#aaa8a6">
          </ThemeSpaceGeneric>
        </space>
      </ThemeSequenceEditor>
    </sequence_editor>
    <text_editor>
      <ThemeTextEditor cursor="#54da70"
                       syntax_special="#ca0c97"
                       line_numbers_background="#a3a3a3"
                       selected_text="#f1e593"
                       syntax_builtin="#3162b2"
                       syntax_comment="#535353"
                       syntax_numbers="#b62440"
                       syntax_string="#c31736">
        <space>
          <ThemeSpaceGeneric header="#aaa8a6"
                             header_text="#000000"
                             header_text_hi="#ffffff"
                             button="#aaa8a6"
                             button_text="#333333"
                             button_text_hi="#ffffff"
                             button_title="#222222"
                             text="#222222"
                             text_hi="#ffffff"
                             title="#000000"
                             back="#aaa8a6">
          </ThemeSpaceGeneric>
        </space>
      </ThemeTextEditor>
    </text_editor>
    <timeline>
      <ThemeTimeline frame_current="#a3ff96"
                     grid="#838383">
        <space>
          <ThemeSpaceGeneric header="#aaa8a6"
                             header_text="#a3a3a3"
                             header_text_hi="#ffffff"
                             button="#aaa8a6"
                             button_text="#222222"
                             button_text_hi="#a3a3a3"
                             button_title="#aeacaa"
                             text="#222222"
                             text_hi="#ffffff"
                             title="#cccccc"
                             back="#aaa8a6">
          </ThemeSpaceGeneric>
        </space>
      </ThemeTimeline>
    </timeline>
    <user_interface>
      <ThemeUserInterface icon_alpha="1"
                          icon_file="">
        <wcol_box>
          <ThemeWidgetColors inner="#aaa8a6ff"
                             inner_sel="#aaa8a6ff"
                             item="#ccccccff"
                             outline="#9f9d9b"
                             shadedown="6"
                             shadetop="0"
                             show_shaded="FALSE"
                             text="#474747"
                             text_sel="#ffffff">
          </ThemeWidgetColors>
        </wcol_box>
        <wcol_list_item>
          <ThemeWidgetColors inner="#f1e59333"
                             inner_sel="#fff29c9a"
                             item="#ffffffff"
                             outline="#8c8a88"
                             shadedown="0"
                             shadetop="0"
                             show_shaded="FALSE"
                             text="#000000"
                             text_sel="#000000">
          </ThemeWidgetColors>
        </wcol_list_item>
        <wcol_menu_back>
          <ThemeWidgetColors inner="#aaa8a6ff"
                             inner_sel="#aaa8a6ff"
                             item="#ccccccff"
                             outline="#474747"
                             shadedown="0"
                             shadetop="0"
                             show_shaded="FALSE"
                             text="#000000"
                             text_sel="#ffffff">
          </ThemeWidgetColors>
        </wcol_menu_back>
        <wcol_menu_item>
          <ThemeWidgetColors inner="#00000000"
                             inner_sel="#aaa8a6ff"
                             item="#000000ff"
                             outline="#474747"
                             shadedown="10"
                             shadetop="-10"
                             show_shaded="TRUE"
                             text="#000000"
                             text_sel="#ffffff">
          </ThemeWidgetColors>
        </wcol_menu_item>
        <wcol_menu>
          <ThemeWidgetColors inner="#aaa8a6ff"
                             inner_sel="#b0aeacff"
                             item="#8e8c8bff"
                             outline="#aaa8a6"
                             shadedown="3"
                             shadetop="-4"
                             show_shaded="TRUE"
                             text="#000000"
                             text_sel="#000000">
          </ThemeWidgetColors>
        </wcol_menu>
        <wcol_num>
          <ThemeWidgetColors inner="#353432ff"
                             inner_sel="#353432ff"
                             item="#222222ff"
                             outline="#050505"
                             shadedown="5"
                             shadetop="-5"
                             show_shaded="FALSE"
                             text="#efefef"
                             text_sel="#ffffff">
          </ThemeWidgetColors>
        </wcol_num>
        <wcol_option>
          <ThemeWidgetColors inner="#a5a3a1ff"
                             inner_sel="#ccc9c7ff"
                             item="#000000ff"
                             outline="#acaaa8"
                             shadedown="0"
                             shadetop="-2"
                             show_shaded="TRUE"
                             text="#676767"
                             text_sel="#000000">
          </ThemeWidgetColors>
        </wcol_option>
        <panel>
          <ThemePanelColors header="#00000004"
                            show_header="TRUE">
          </ThemePanelColors>
        </panel>
        <wcol_progress>
          <ThemeWidgetColors inner="#aaa8a6ff"
                             inner_sel="#aaa8a6ff"
                             item="#96c78eff"
                             outline="#474747"
                             shadedown="-3"
                             shadetop="3"
                             show_shaded="TRUE"
                             text="#000000"
                             text_sel="#ffffff">
          </ThemeWidgetColors>
        </wcol_progress>
        <wcol_pulldown>
          <ThemeWidgetColors inner="#aaa8a6ff"
                             inner_sel="#aaa8a6ff"
                             item="#ccccccff"
                             outline="#474747"
                             shadedown="-20"
                             shadetop="25"
                             show_shaded="FALSE"
                             text="#000000"
                             text_sel="#ffffff">
          </ThemeWidgetColors>
        </wcol_pulldown>
        <wcol_radio>
          <ThemeWidgetColors inner="#a8a6a4ff"
                             inner_sel="#95adc1ff"
                             item="#aaa8a6ff"
                             outline="#aaa8a6"
                             shadedown="1"
                             shadetop="-2"
                             show_shaded="TRUE"
                             text="#1a1a1a"
                             text_sel="#1a1a1a">
          </ThemeWidgetColors>
        </wcol_radio>
        <wcol_regular>
          <ThemeWidgetColors inner="#7b7978ff"
                             inner_sel="#95adc1ff"
                             item="#979594ff"
                             outline="#5f5e5c"
                             shadedown="0"
                             shadetop="-2"
                             show_shaded="TRUE"
                             text="#1a1a1a"
                             text_sel="#1a1a1a">
          </ThemeWidgetColors>
        </wcol_regular>
        <wcol_scroll>
          <ThemeWidgetColors inner="#a4a2a0ff"
                             inner_sel="#aaa8a6ff"
                             item="#a2a19fff"
                             outline="#82807f"
                             shadedown="-5"
                             shadetop="4"
                             show_shaded="TRUE"
                             text="#000000"
                             text_sel="#ffffff">
          </ThemeWidgetColors>
        </wcol_scroll>
        <wcol_numslider>
          <ThemeWidgetColors inner="#353432ff"
                             inner_sel="#353432ff"
                             item="#1f1f1fff"
                             outline="#050505"
                             shadedown="5"
                             shadetop="-5"
                             show_shaded="FALSE"
                             text="#ffffff"
                             text_sel="#ffffff">
          </ThemeWidgetColors>
        </wcol_numslider>
        <wcol_state>
          <ThemeWidgetStateColors inner_anim="#adb4c7"
                                  inner_anim_sel="#c4cee0"
                                  blend="1"
                                  inner_driven="#c69cb1"
                                  inner_driven_sel="#ecaacd"
                                  inner_key="#c0bb83"
                                  inner_key_sel="#dad37d">
          </ThemeWidgetStateColors>
        </wcol_state>
        <wcol_text>
          <ThemeWidgetColors inner="#a6a4a2ff"
                             inner_sel="#f1e593ff"
                             item="#c2b876ff"
                             outline="#aaa8a6"
                             shadedown="0"
                             shadetop="-2"
                             show_shaded="TRUE"
                             text="#242424"
                             text_sel="#242424">
          </ThemeWidgetColors>
        </wcol_text>
        <wcol_toggle>
          <ThemeWidgetColors inner="#a8a6a4ff"
                             inner_sel="#95adc1ff"
                             item="#aaa8a6ff"
                             outline="#aaa8a6"
                             shadedown="0"
                             shadetop="-3"
                             show_shaded="TRUE"
                             text="#1c1c1c"
                             text_sel="#1a1a1a">
          </ThemeWidgetColors>
        </wcol_toggle>
        <wcol_tool>
          <ThemeWidgetColors inner="#aaa8a6ff"
                             inner_sel="#a19f9dff"
                             item="#a19f9dff"
                             outline="#a6a4a2"
                             shadedown="-6"
                             shadetop="5"
                             show_shaded="TRUE"
                             text="#000000"
                             text_sel="#ffffff">
          </ThemeWidgetColors>
        </wcol_tool>
        <wcol_tooltip>
          <ThemeWidgetColors inner="#191919e6"
                             inner_sel="#2d2d2de6"
                             item="#646464ff"
                             outline="#000000"
                             shadedown="-20"
                             shadetop="25"
                             show_shaded="FALSE"
                             text="#ffffff"
                             text_sel="#ffffff">
          </ThemeWidgetColors>
        </wcol_tooltip>
      </ThemeUserInterface>
    </user_interface>
    <user_preferences>
      <ThemeUserPreferences>
        <space>
          <ThemeSpaceGeneric header="#aaa8a6"
                             header_text="#000000"
                             header_text_hi="#ffffff"
                             button="#aaa8a6"
                             button_text="#000000"
                             button_text_hi="#ffffff"
                             button_title="#000000"
                             text="#222222"
                             text_hi="#ffffff"
                             title="#222222"
                             back="#aaa8a6">
          </ThemeSpaceGeneric>
        </space>
      </ThemeUserPreferences>
    </user_preferences>
    <bone_color_sets>
      <ThemeBoneColorSet active="#f70a0a"
                         show_colored_constraints="FALSE"
                         normal="#9a0000"
                         select="#bd1111">
      </ThemeBoneColorSet>
      <ThemeBoneColorSet active="#fa9900"
                         show_colored_constraints="FALSE"
                         normal="#f74018"
                         select="#f66913">
      </ThemeBoneColorSet>
      <ThemeBoneColorSet active="#83ef1d"
                         show_colored_constraints="FALSE"
                         normal="#1e9109"
                         select="#59b70b">
      </ThemeBoneColorSet>
      <ThemeBoneColorSet active="#5ec1ef"
                         show_colored_constraints="FALSE"
                         normal="#0a3694"
                         select="#3667df">
      </ThemeBoneColorSet>
      <ThemeBoneColorSet active="#f05d91"
                         show_colored_constraints="FALSE"
                         normal="#a9294e"
                         select="#c1416a">
      </ThemeBoneColorSet>
      <ThemeBoneColorSet active="#8764d5"
                         show_colored_constraints="FALSE"
                         normal="#430c78"
                         select="#543aa3">
      </ThemeBoneColorSet>
      <ThemeBoneColorSet active="#6fb6ab"
                         show_colored_constraints="FALSE"
                         normal="#24785a"
                         select="#3c9579">
      </ThemeBoneColorSet>
      <ThemeBoneColorSet active="#9bc2cd"
                         show_colored_constraints="FALSE"
                         normal="#4b707c"
                         select="#6a8691">
      </ThemeBoneColorSet>
      <ThemeBoneColorSet active="#f3ff00"
                         show_colored_constraints="FALSE"
                         normal="#f4c90c"
                         select="#eec236">
      </ThemeBoneColorSet>
      <ThemeBoneColorSet active="#ffffff"
                         show_colored_constraints="FALSE"
                         normal="#1e2024"
                         select="#484c56">
      </ThemeBoneColorSet>
      <ThemeBoneColorSet active="#d330d6"
                         show_colored_constraints="FALSE"
                         normal="#6f2f6a"
                         select="#9845be">
      </ThemeBoneColorSet>
      <ThemeBoneColorSet active="#bbef5b"
                         show_colored_constraints="FALSE"
                         normal="#6c8e22"
                         select="#7fb022">
      </ThemeBoneColorSet>
      <ThemeBoneColorSet active="#dedede"
                         show_colored_constraints="FALSE"
                         normal="#8d8d8d"
                         select="#b0b0b0">
      </ThemeBoneColorSet>
      <ThemeBoneColorSet active="#bd6a11"
                         show_colored_constraints="FALSE"
                         normal="#834326"
                         select="#8b5811">
      </ThemeBoneColorSet>
      <ThemeBoneColorSet active="#34622b"
                         show_colored_constraints="FALSE"
                         normal="#08310e"
                         select="#1c430b">
      </ThemeBoneColorSet>
      <ThemeBoneColorSet active="#000000"
                         show_colored_constraints="FALSE"
                         normal="#000000"
                         select="#000000">
      </ThemeBoneColorSet>
      <ThemeBoneColorSet active="#000000"
                         show_colored_constraints="FALSE"
                         normal="#000000"
                         select="#000000">
      </ThemeBoneColorSet>
      <ThemeBoneColorSet active="#000000"
                         show_colored_constraints="FALSE"
                         normal="#000000"
                         select="#000000">
      </ThemeBoneColorSet>
      <ThemeBoneColorSet active="#000000"
                         show_colored_constraints="FALSE"
                         normal="#000000"
                         select="#000000">
      </ThemeBoneColorSet>
      <ThemeBoneColorSet active="#000000"
                         show_colored_constraints="FALSE"
                         normal="#000000"
                         select="#000000">
      </ThemeBoneColorSet>
    </bone_color_sets>
  </Theme>
</bpy>
